[1,["ecpdLyjvZBwrvm+cedCcQy","5e6WDQlnRPNIv+WRpxL/ID","094yLYQFdI+I+IvrvL8R9n","a2MjXRFdtLlYQ5ouAFv/+R","d3ViET54dFY6CT1xzkZyGd","6c4Fl9j8dB+o2S6ryFFLAd","d34lA/LX9JMrJbnqh3iN0d","50g9yit/BIgbLEk6oSzaNb","a1U5RdJRFMFL57BdJC9H1X","b8key+gM5D5LXd1F2xkLKd","24pxjDwTNNaoQ+Ol7z6uO0","50enP9twpHB59chei2zTrq","9dGurQW+9PlropQDmyrDhT","150h0KubxIz74KADxnllnu","f8HUdO6pxPM5URmGnWvAZs","ddX0uLLp1GbLy6TINJE05Z","2aqy6Z+hlDVp4+j771eE7z","5czKFYNNFDLaZlEiUsCsi+","3dUuJlvwtOo7ViX8OKaFFj","b2/7Gx2hJIbrxCSEKOhQw7","77kdb+TTBMgoFqiyShk+xS","02delMVqdBD70a/HSD99FK","1060ptt11Kb6q47cgpkXcs"],["node","_spriteFrame","_textureSetter","_parent","_N$file","root","data","prefab","_N$target","bgsound","foodGroup","result","board","colliderHead","scene","snakehitsound","mysound"],[["cc.Node",["_name","_zIndex","_groupIndex","_opacity","_id","_active","_components","_contentSize","_trs","_parent","_children","_anchorPoint","_prefab","_eulerAngles"],-3,9,5,7,1,2,5,4,5],"cc.SpriteFrame",["cc.Widget",["_alignFlags","_left","_bottom","_isAbsLeft","_right","_isAbsBottom","_isAbsRight","_originalWidth","_originalHeight","_top","_isAbsTop","node"],-8,1],["cc.Node",["_name","_zIndex","_groupIndex","_components","_contentSize","_trs","_anchorPoint","_parent","_children","_color","_eulerAngles"],0,12,5,7,5,1,2,5,5],["cc.Node",["_name","_zIndex","_parent","_components","_contentSize","_trs","_children","_color","_eulerAngles"],1,1,2,5,7,2,5,5],["cc.Sprite",["_sizeMode","_type","_enabled","_fillType","_fillRange","node","_materials","_spriteFrame","_fillCenter"],-2,1,3,6,5],["cc.Label",["_string","_isSystemFontUsed","_fontSize","_lineHeight","_srcBlendFactor","_N$horizontalAlign","_N$verticalAlign","node","_materials","_N$file"],-4,1,3,6],["cc.BoxCollider",["tag","node","_size","_offset"],2,1,5,5],["25accHi+oRJF5bQuo9BngWW",["foodColor","node"],2,1],["cc.TTFFont",["_name","_native"],1],["cc.Prefab",["_name"],2],["cc.PrefabInfo",["root"],3,1],["cc.AudioClip",["_name","_native","duration"],0],["cc.SceneAsset",["_name","asyncLoadAssets"],1],["cc.Canvas",["_fitWidth","node","_designResolution"],2,1,5],["1d8dcUhh0xA6oFno4wwupOs",["node","colliderHead","board","result","foodGroup"],3,1,1,1,1,1],["cc.BlockInputEvents",["node"],3,1],["3a90cmdI59ErJw75snyGN9l",["node","bg"],3,1,2],["cc.Button",["duration","_N$transition","node","_N$pressedColor","_N$disabledColor","_N$target"],1,1,5,5,1],["cc.Scene",["_name","_active","_zIndex","_children","_anchorPoint","_trs"],0,2,5,7],["cc.Camera",["_clearFlags","_depth","node"],1,1],["07d3fDIgBxPVLGivwEXJ/0R",["node"],3,1],["cc.Graphics",["_lineWidth","_lineCap","node","_materials","_strokeColor"],1,1,3,5],["51447MZm/tKYpHqojpv91ke",["node","graphics","head_collide"],3,1,1,1],["bd819tql8VIUJeEfWxKP5oG",["node","foods","food_produce_posY"],3,1,9,1],["Foods",["name","initPollCount","prefab"],1,6],["8d18c2Se7RIgJdPdYCE8D2k",["node","score","end_score","game_over","btn_exit","btn_restart","lb_revive_count","head","circle_timer"],3,1,1,1,1,1,1,1,1,1]],[[5,0,5,6,7,2],[2,0,11,2],[7,0,1,2,2],[10,0,2],[0,0,1,2,6,12,7,8,13,4],[11,0,1],[25,0,1,2,3],[0,0,1,9,10,6,7,11,8,3],[8,0,1,2],[0,0,1,9,6,7,8,3],[0,0,1,2,9,6,7,8,4],[12,0,1,2,4],[2,0,9,10,11,4],[16,0,1],[18,0,1,2,3,4,5,3],[6,4,0,2,3,1,5,6,7,8,8],[9,0,1,3],[0,0,1,4,10,6,7,8,4],[0,0,1,10,6,7,8,3],[0,0,3,1,9,6,7,11,4],[0,0,3,1,9,6,7,11,8,4],[0,0,1,2,9,10,6,7,11,8,4],[0,0,1,9,10,6,7,8,3],[0,0,5,3,1,2,9,6,7,11,8,6],[0,0,1,6,7,8,3],[0,0,1,9,6,8,3],[3,0,1,2,3,9,4,5,10,4],[3,0,1,8,3,4,6,3],[3,0,1,7,8,3,4,6,5,3],[3,0,1,7,3,4,6,5,3],[3,0,1,7,3,4,5,3],[4,0,2,6,3,4,2],[4,0,1,2,3,3],[4,0,1,2,3,7,4,5,3],[4,0,2,3,4,5,8,2],[5,2,0,5,6,7,3],[5,1,0,5,6,7,3],[5,1,3,4,5,6,8,4],[8,1,1],[7,1,2,1],[7,1,3,2,1],[13,0,1,3],[14,0,1,2,2],[15,0,1,2,3,4,1],[2,0,1,2,3,5,11,6],[2,0,4,2,6,5,11,6],[2,0,7,8,11,4],[2,0,9,2,7,8,11,6],[2,0,1,4,3,6,11,6],[2,0,1,11,3],[2,0,1,4,3,11,5],[17,0,1,1],[6,0,1,7,8,9,3],[6,4,0,2,3,1,5,6,7,8,9,8],[6,0,2,3,1,7,8,5],[19,0,1,2,3,4,5,4],[20,0,1,2,3],[21,0,1],[22,0,1,2,3,4,3],[23,0,1,2,1],[24,0,1,2,1],[26,0,1,2,3,4,5,6,7,8,1]],[[[{"name":"blue","rect":[729,654,230,230],"offset":[0,0],"originalSize":[230,230],"capInsets":[0,0,0,0]}],[1],0,[0],[2],[1]],[[[16,"DoppioOne-Regular","DoppioOne-Regular.ttf"],-1],0,0,[],[],[]],[[[3,"yellow-food"],[4,"yellow-food",0,2,[[0,0,-2,[0],1],[8,3,-3],[2,1,-4,[5,27,27]]],[5,-1],[5,40,40],[363,776,0,0,0,-0.3826834323650898,0.9238795325112867,1,1,1],[1,0,0,-45]]],0,[0,5,1,0,0,1,0,0,1,0,0,1,0,6,1,4],[0,0],[-1,1],[0,6]],[[[11,"SnakeHit",".mp3",0.604],-1],0,0,[],[],[]],[[[3,"red-food"],[4,"red-food",0,2,[[0,0,-2,[0],1],[38,-3],[2,1,-4,[5,27,27]]],[5,-1],[5,40,40],[260,711,0,0,0,-0.3826834323650898,0.9238795325112867,1,1,1],[1,0,0,-45]]],0,[0,5,1,0,0,1,0,0,1,0,0,1,0,6,1,4],[0,0],[-1,1],[0,7]],[[{"name":"red","rect":[729,890,230,228],"offset":[0,0],"originalSize":[230,228],"rotated":1,"capInsets":[0,0,0,0]}],[1],0,[0],[2],[1]],[[[41,"game",null],[17,"Canvas",0,"d8JMg6ZQhF5bedWkrIIZNm",[-9,-10,-11,-12,-13,-14,-15],[[42,true,-1,[5,750,1334]],[43,-6,-5,-4,-3,-2],[1,45,-7],[0,0,-8,[25],26]],[5,750,1334],[375,667,0,0,0,0,1,1,1,1]],[18,"game-over",0,[-19,-20,-21,-22],[[1,45,-16],[35,false,0,-17,[23],24],[13,-18]],[5,750,1334],[375,667,0,0,0,0,1,1,1,1]],[26,"head",0,1,[[[0,0,-23,[6],7],[39,-24,[5,20,20]],-25,[13,-26]],4,4,1,4],[4,4278190335],[5,20,20],[380,300,0,0,0,-0.3826834323650898,0.9238795325112867,1,1,1],[1,0,0,-45]],[7,"background",0,1,[-31,-32,-33],[[1,45,-27],[51,-30,[-28,-29]]],[5,750,1334],[0,0,0],[-375,-667,0,0,0,0,1,1,1,1]],[9,"nothanks",0,2,[[14,0.2,3,-35,[4,4294967295],[4,4294967295],-34],[44,12,0.36699333333333334,0.022155922038980494,false,false,-36],[52,"No,Thanks",false,-37,[17],18]],[5,199.51,50.4],[0,-612.244,0,0,0,0,1,1,1,0]],[9,"restart",0,2,[[36,1,0,-38,[19],20],[14,0.2,3,-40,[4,4294967295],[4,4294967295],-39],[45,36,0.203,0.19581409295352323,false,false,-41]],[5,891,475],[0,-287.034,0,0,0,0,1,0.5,0.5,0]],[27,"board",0,[3,-44],[[[1,45,-42],-43],4,1],[5,750,1334],[0,0,0]],[28,"result",0,1,[-47,2],[[[1,45,-45],-46],4,1],[5,750,1334],[0,0,0],[-375,-667,0,0,0,0,1,1,1,1]],[19,"bg",70,0,4,[[0,0,-48,[0],1],[46,45,750,1334,-49]],[5,750,1334],[0,0,0]],[20,"bg",70,0,4,[[0,0,-50,[2],3],[47,45,-1334,1334,750,1334,-51]],[5,750,1334],[0,0,0],[0,1334,0,0,0,0,1,1,1,1]],[21,"wall",0,3,1,[-53,-54],[[1,45,-52]],[5,750,1334],[0,0,0],[-375,-667,0,0,0,0,1,1,1,1]],[22,"end-score-text",0,2,[-57],[[53,1,"SCORE",60,65,false,1,1,-55,[15],16],[12,17,0.18890554722638683,false,-56]],[5,115.56,81.9],[0,365.86,0,0,0,0,1,1.2,1.2,1]],[23,"New Sprite(Splash)",false,139.485,0,1,4,[[0,0,-58,[4],5],[40,-59,[0,83,50],[5,166,100]]],[5,166,100],[0,0,0],[100,300,0,0,0,0,1,1,1,1]],[7,"snake",0,1,[7],[[1,45,-60]],[5,750,1334],[0,0,0],[-375,-667,0,0,0,0,1,1,1,1]],[29,"food",0,1,[[[1,45,-61],-62],4,1],[5,750,1334],[0,0,0],[-375,-667,0,0,0,0,1,1,1,1]],[24,"food-produce-pos",0,[[48,40,0.026666666666666665,0.026666666666666665,false,false,-63]],[5,710,50],[375,1439,0,0,0,0,1,1,1,1]],[7,"pos",0,1,[16],[[1,45,-64]],[5,750,1334],[0,0,0],[-375,-667,0,0,0,0,1,1,1,1]],[10,"left-1",0,3,11,[[49,13,-20,-65],[2,9,-66,[5,20,1334]]],[5,20,1334],[-10,667,0,0,0,0,1,1,1,1]],[10,"right-1",0,3,11,[[50,37,0.66,-20,false,-67],[2,9,-68,[5,20,1334]]],[5,20,1334],[760,667,0,0,0,0,1,1,1,1]],[30,"score",0,8,[[-69,[12,17,0.06217916041978994,false,-70]],1,4],[5,31.68,107.1],[375,1181.438,0,0,0,0,1,1.3,1.3,1.3]],[31,"revivecount",2,[-72],[-71],[5,55.44,189]],[55,"New Node",false,0,[1],[0,0,0],[0,0,0,0,0,0,1,1,1,1]],[25,"Main Camera",0,1,[[56,7,-1,-73]],[0,0,284.3386946007803,0,0,0,1,1,1,1]],[57,3],[32,"g",0,7,[-74]],[58,20,2,25,[8],[4,4278190335]],[59,7,26,3],[60,15,[[6,"blue-food",10,9],[6,"yellow-food",10,10],[6,"red-food",10,11],[6,"green-food",10,12]],16],[15,1,"0",80,85,false,1,1,20,[13]],[33,"end-score-num",0,12,[-75],[4,4278250751],[5,221.76,189],[0,-86.681,0,0,0,0,1,1,1,1]],[15,1,"0000",140,150,false,1,1,30,[14]],[34,"CIRCULAR_TIMER",21,[-76],[5,382,382],[0,22,0,0,0,0.7071067811865475,0.7071067811865476,0.57,0.57,0.758],[1,0,0,90]],[37,3,2,1,32,[21],[0,0.5,0.5]],[54,"5",140,150,false,21,[22]],[61,8,29,31,2,5,6,34,3,33]],0,[0,0,1,0,10,28,0,11,35,0,12,27,0,13,24,0,0,1,0,0,1,0,0,1,0,-1,23,0,-2,4,0,-3,14,0,-4,15,0,-5,17,0,-6,11,0,-7,8,0,0,2,0,0,2,0,0,2,0,-1,12,0,-2,5,0,-3,6,0,-4,21,0,0,3,0,0,3,0,-3,24,0,0,3,0,0,4,0,-1,9,0,-2,10,0,0,4,0,-1,9,0,-2,10,0,-3,13,0,8,5,0,0,5,0,0,5,0,0,5,0,0,6,0,8,6,0,0,6,0,0,6,0,0,7,0,-2,27,0,-2,25,0,0,8,0,-2,35,0,-1,20,0,0,9,0,0,9,0,0,10,0,0,10,0,0,11,0,-1,18,0,-2,19,0,0,12,0,0,12,0,-1,30,0,0,13,0,0,13,0,0,14,0,0,15,0,-2,28,0,0,16,0,0,17,0,0,18,0,0,18,0,0,19,0,0,19,0,-1,29,0,0,20,0,-1,34,0,-1,32,0,0,23,0,-1,26,0,-1,31,0,-1,33,0,14,22,1,3,22,2,3,8,3,3,7,7,3,14,16,3,17,76],[0,0,0,0,0,0,0,0,0,0,0,0,0,0,0,0,0,0,0,0,0,0,0,0,0,0,0,27,27,29,31,33,34,35,35],[-1,1,-1,1,-1,1,-1,1,-1,7,7,7,7,-1,-1,-1,4,-1,4,-1,1,-1,-1,-1,1,-1,1,9,15,4,4,1,4,16,9],[0,4,0,4,0,3,0,3,8,9,10,11,12,0,0,0,2,0,13,0,14,0,0,0,3,0,15,5,16,2,2,17,2,18,5]],[[{"name":"CIRCULAR_TIMER","rect":[0,0,382,382],"offset":[0,0],"originalSize":[382,382],"capInsets":[0,0,0,0]}],[1],0,[0],[2],[19]],[[[11,"Like Sky_CS_BgMusic",".mp3",79.488],-1],0,0,[],[],[]],[[{"name":"green","rect":[1644,1369,230,227],"offset":[0,0],"originalSize":[230,227],"capInsets":[0,0,0,0]}],[1],0,[0],[2],[1]],[[[3,"green-food"],[4,"green-food",0,2,[[0,0,-2,[0],1],[8,1,-3],[2,1,-4,[5,27,27]]],[5,-1],[5,40,40],[372,631,0,0,0,-0.3826834323650898,0.9238795325112867,1,1,1],[1,0,0,-45]]],0,[0,5,1,0,0,1,0,0,1,0,0,1,0,6,1,4],[0,0],[-1,1],[0,20]],[[{"name":"default_sprite_splash","rect":[0,0,2,2],"offset":[0,0],"originalSize":[2,2],"capInsets":[0,0,0,0]}],[1],0,[0],[2],[21]],[[[3,"blue-food"],[4,"blue-food",0,2,[[0,0,-2,[0],1],[8,2,-3],[2,1,-4,[5,27,27]]],[5,-1],[5,40,40],[479,717,0,0,0,-0.3826834323650898,0.9238795325112867,1,1,1],[1,0,0,-45]]],0,[0,5,1,0,0,1,0,0,1,0,0,1,0,6,1,4],[0,0],[-1,1],[0,22]],[[{"name":"stars","rect":[729,3,645,1279],"offset":[2.5,0.5],"originalSize":[720,1280],"rotated":1,"capInsets":[0,0,0,0]}],[1],0,[0],[2],[1]],[[{"name":"yellow","rect":[1644,1135,230,228],"offset":[0,0],"originalSize":[230,228],"capInsets":[0,0,0,0]}],[1],0,[0],[2],[1]],[[{"name":"plain","rect":[3,3,720,1280],"offset":[0,0],"originalSize":[720,1280],"capInsets":[0,0,0,0]}],[1],0,[0],[2],[1]],[[{"name":"revive","rect":[1145,654,891,475],"offset":[0,0],"originalSize":[903,485],"capInsets":[0,0,0,0]}],[1],0,[0],[2],[1]]]]